declarative/__init__.py
declarative/auto_version.py
declarative/metaclass.py
declarative/overridable_object.py
declarative/run.py
declarative/version.py
declarative/argparse/__init__.py
declarative/argparse/annotations.py
declarative/argparse/oo_argparse.py
declarative/bunch/__init__.py
declarative/bunch/bunch.py
declarative/bunch/deep_bunch.py
declarative/bunch/depbunch.py
declarative/bunch/hdf_deep_bunch.py
declarative/bunch/quickbunch.py
declarative/bunch/shadow_bunch.py
declarative/bunch/tag_bunch.py
declarative/callbacks/__init__.py
declarative/callbacks/callbacks.py
declarative/callbacks/relay.py
declarative/callbacks/state_booleans.py
declarative/callbacks/validators.py
declarative/properties/__init__.py
declarative/properties/bases.py
declarative/properties/memoized.py
declarative/properties/memoized_adv.py
declarative/properties/memoized_adv_group.py
declarative/properties/utilities.py
declarative/utilities/__init__.py
declarative/utilities/future3.py
declarative/utilities/future_from_2.py
declarative/utilities/interrupt_delay.py
declarative/utilities/representations.py
declarative/utilities/super_base.py
declarative/utilities/unique.py
declarative-1.3.2.dist-info/LICENSE
declarative-1.3.2.dist-info/METADATA
declarative-1.3.2.dist-info/WHEEL
declarative-1.3.2.dist-info/top_level.txt
declarative-1.3.2.dist-info/zip-safe
declarative-1.3.2.dist-info/RECORD
